Security_Module/__init__.py
Security_Module/main.py
Security_Module-0.0.1.dist-info/LICENSE
Security_Module-0.0.1.dist-info/METADATA
Security_Module-0.0.1.dist-info/WHEEL
Security_Module-0.0.1.dist-info/top_level.txt
Security_Module-0.0.1.dist-info/RECORD
