Metadata-Version: 2.1
Name: Security_Module
Version: 0.0.1
Summary: Telegram Bot Security Module
Classifier: Programming Language :: Python :: 3
Classifier: License :: OSI Approved :: MIT License
Classifier: Operating System :: OS Independent
Requires-Python: >=3.6
License-File: LICENSE
